arcaflow_plugin_sdk/__init__.py
arcaflow_plugin_sdk/annotations.py
arcaflow_plugin_sdk/atp.py
arcaflow_plugin_sdk/jsonschema.py
arcaflow_plugin_sdk/plugin.py
arcaflow_plugin_sdk/predefined_schemas.py
arcaflow_plugin_sdk/schema.py
arcaflow_plugin_sdk/serialization.py
arcaflow_plugin_sdk/test_atp.py
arcaflow_plugin_sdk/test_jsonschema.py
arcaflow_plugin_sdk/test_plugin.py
arcaflow_plugin_sdk/test_schema.py
arcaflow_plugin_sdk/validation.py
arcaflow_plugin_sdk-0.14.4.dist-info/LICENSE
arcaflow_plugin_sdk-0.14.4.dist-info/METADATA
arcaflow_plugin_sdk-0.14.4.dist-info/WHEEL
arcaflow_plugin_sdk-0.14.4.dist-info/RECORD
