Metadata-Version: 2.1
Name: arcaflow-plugin-sdk
Version: 0.14.4
Summary: Plugin SDK for Python for the Arcaflow workflow engine
Home-page: https://github.com/arcalot/arcaflow-plugin-sdk-python
License: Apache-2.0
Author: Arcalot Contributors
Requires-Python: >=3.12,<4.0
Classifier: License :: OSI Approved :: Apache Software License
Classifier: Operating System :: OS Independent
Classifier: Programming Language :: Python :: 3
Classifier: Programming Language :: Python :: 3
Requires-Dist: PyYAML (>=6.0.1,<6.1.0)
Requires-Dist: cbor2 (>=5.6.0,<5.7.0)
Project-URL: Bug Tracker, https://github.com/arcalot/arcaflow-plugin-sdk-python/issues
